python_trade_runner/__init__.py
python_trade_runner/backtest.py
python_trade_runner/chart.py
python_trade_runner/constants.py
python_trade_runner/data.py
python_trade_runner/drawdowns.py
python_trade_runner/infos.py
python_trade_runner/pattern.py
python_trade_runner/setup.py
python_trade_runner/trade.py
python_trade_runner/utils.py
python_trade_runner/version.py
python_trade_runner/visuals.py
python_trade_runner-0.0.2.dev1.dist-info/LICENSE.txt
python_trade_runner-0.0.2.dev1.dist-info/METADATA
python_trade_runner-0.0.2.dev1.dist-info/WHEEL
python_trade_runner-0.0.2.dev1.dist-info/top_level.txt
python_trade_runner-0.0.2.dev1.dist-info/RECORD
